{"v":"5.9.0","fr":60,"ip":0,"op":61,"w":1000,"h":1000,"nm":"Revoke_Loop","ddd":0,"assets":[],"layers":[{"ddd":0,"ind":1,"ty":3,"nm":"Null 7","sr":1,"ks":{"o":{"a":0,"k":0,"ix":11},"r":{"a":0,"k":0,"ix":10},"p":{"s":true,"x":{"a":0,"k":500,"ix":3},"y":{"a":1,"k":[{"i":{"x":[0.04],"y":[1]},"o":{"x":[0.35],"y":[0]},"t":-30,"s":[1510]},{"i":{"x":[0.833],"y":[1]},"o":{"x":[0.35],"y":[0]},"t":-20,"s":[500]},{"i":{"x":[0.95],"y":[0.471]},"o":{"x":[0.85],"y":[0]},"t":10,"s":[500]},{"t":30,"s":[-626]}],"ix":4}},"a":{"a":0,"k":[0,0,0],"ix":1,"l":2},"s":{"a":0,"k":[100,100,100],"ix":6,"l":2}},"ao":0,"ip":-30,"op":40,"st":-30,"bm":0},{"ddd":0,"ind":2,"ty":4,"nm":"line 2","parent":1,"sr":1,"ks":{"o":{"a":0,"k":100,"ix":11},"r":{"a":0,"k":0,"ix":10},"p":{"a":0,"k":[0,0,0],"ix":2,"l":2},"a":{"a":0,"k":[0,0,0],"ix":1,"l":2},"s":{"a":0,"k":[100,100,100],"ix":6,"l":2}},"ao":0,"shapes":[{"ind":0,"ty":"sh","ix":1,"ks":{"a":0,"k":{"i":[[0,0],[0,0]],"o":[[0,0],[0,0]],"v":[[-499.875,-499.875],[579.25,579.5]],"c":false},"ix":2},"nm":"Path 1","mn":"ADBE Vector Shape - Group","hd":false},{"ty":"tm","s":{"a":0,"k":0,"ix":1},"e":{"a":1,"k":[{"i":{"x":[0.04],"y":[1]},"o":{"x":[0.35],"y":[0]},"t":-20,"s":[0]},{"t":0,"s":[100]}],"ix":2},"o":{"a":0,"k":0,"ix":3},"m":1,"ix":2,"nm":"Trim Paths 1","mn":"ADBE Vector Filter - Trim","hd":false},{"ty":"st","c":{"a":0,"k":[0.964705884457,0.972549021244,0.996078431606,1],"ix":3},"o":{"a":0,"k":100,"ix":4},"w":{"a":0,"k":177,"ix":5},"lc":1,"lj":1,"ml":4,"bm":0,"nm":"Stroke 1","mn":"ADBE Vector Graphic - Stroke","hd":false}],"ip":-30,"op":40,"st":-30,"bm":0},{"ddd":0,"ind":3,"ty":4,"nm":"mask 2","parent":1,"td":1,"sr":1,"ks":{"o":{"a":0,"k":100,"ix":11},"r":{"a":0,"k":0,"ix":10},"p":{"a":0,"k":[0,0,0],"ix":2,"l":2},"a":{"a":0,"k":[0,0,0],"ix":1,"l":2},"s":{"a":0,"k":[100,100,100],"ix":6,"l":2}},"ao":0,"shapes":[{"ind":0,"ty":"sh","ix":1,"ks":{"a":0,"k":{"i":[[0,0],[0,0]],"o":[[0,0],[0,0]],"v":[[-499.875,-499.875],[500.25,500.5]],"c":false},"ix":2},"nm":"Path 1","mn":"ADBE Vector Shape - Group","hd":false},{"ty":"tm","s":{"a":0,"k":0,"ix":1},"e":{"a":1,"k":[{"i":{"x":[0.04],"y":[1]},"o":{"x":[0.35],"y":[0]},"t":-20,"s":[0]},{"t":-4,"s":[100]}],"ix":2},"o":{"a":0,"k":0,"ix":3},"m":1,"ix":2,"nm":"Trim Paths 1","mn":"ADBE Vector Filter - Trim","hd":false},{"ty":"st","c":{"a":0,"k":[1,0,0,1],"ix":3},"o":{"a":0,"k":100,"ix":4},"w":{"a":0,"k":362,"ix":5},"lc":1,"lj":1,"ml":4,"bm":0,"nm":"Stroke 1","mn":"ADBE Vector Graphic - Stroke","hd":false}],"ip":-30,"op":40,"st":-30,"bm":0},{"ddd":0,"ind":4,"ty":4,"nm":"chain 2","parent":1,"tt":2,"sr":1,"ks":{"o":{"a":0,"k":100,"ix":11},"r":{"a":0,"k":0,"ix":10},"p":{"a":0,"k":[-0.001,0,0],"ix":2,"l":2},"a":{"a":0,"k":[0,0,0],"ix":1,"l":2},"s":{"a":0,"k":[100,100,100],"ix":6,"l":2}},"ao":0,"shapes":[{"ty":"gr","it":[{"ty":"gr","it":[{"ind":0,"ty":"sh","ix":1,"ks":{"a":0,"k":{"i":[[113.903,113.903],[74.644,0],[56.953,-56.952],[0,0],[0,0],[-113.903,-113.903],[-74.644,0],[-56.953,56.951],[0,0],[0,0],[0,0],[0,0],[0,0],[0,0]],"o":[[-56.952,-56.951],[-74.644,0],[0,0],[0,0],[-113.903,113.903],[56.952,56.951],[74.644,0],[0,0],[0,0],[0,0],[0,0],[0,0],[0,0],[113.903,-113.904]],"v":[[414.572,-414.573],[208.334,-500],[2.095,-414.573],[-78.712,-333.767],[-414.572,2.094],[-414.572,414.573],[-208.332,500],[-2.093,414.573],[78.714,333.767],[78.714,333.767],[88.06,324.42],[90.466,322.014],[90.466,322.014],[414.572,-2.094]],"c":true},"ix":2},"nm":"Path 1","mn":"ADBE Vector Shape - Group","hd":false},{"ty":"tr","p":{"a":0,"k":[0,0],"ix":2},"a":{"a":0,"k":[0,0],"ix":1},"s":{"a":0,"k":[100,100],"ix":3},"r":{"a":0,"k":0,"ix":6},"o":{"a":0,"k":100,"ix":7},"sk":{"a":0,"k":0,"ix":4},"sa":{"a":0,"k":0,"ix":5},"nm":"Transform"}],"nm":"Group 1","np":1,"cix":2,"bm":0,"ix":1,"mn":"ADBE Vector Group","hd":false},{"ty":"gr","it":[{"ind":0,"ty":"sh","ix":1,"ks":{"a":0,"k":{"i":[[19.674,-19.674],[0,0],[0,0],[0,0],[27.823,0],[19.674,19.675],[0,27.823],[-19.674,19.674],[0,0],[0,0],[-27.823,0],[-19.674,-19.675],[0,-27.824]],"o":[[0,0],[0,0],[0,0],[-19.675,19.676],[-27.823,0],[-19.674,-19.674],[0,-27.823],[0,0],[0,0],[19.675,-19.675],[27.823,0],[19.674,19.674],[0,27.824]],"v":[[281.989,-134.677],[-53.87,201.183],[-53.869,201.184],[-134.676,281.99],[-208.332,312.5],[-281.989,281.99],[-312.499,208.333],[-281.989,134.677],[53.871,-201.184],[134.676,-281.99],[208.332,-312.5],[281.989,-281.99],[312.499,-208.333]],"c":true},"ix":2},"nm":"Path 1","mn":"ADBE Vector Shape - Group","hd":false},{"ty":"tr","p":{"a":0,"k":[0.001,0],"ix":2},"a":{"a":0,"k":[0,0],"ix":1},"s":{"a":0,"k":[100,100],"ix":3},"r":{"a":0,"k":0,"ix":6},"o":{"a":0,"k":100,"ix":7},"sk":{"a":0,"k":0,"ix":4},"sa":{"a":0,"k":0,"ix":5},"nm":"Transform"}],"nm":"Group 2","np":1,"cix":2,"bm":0,"ix":2,"mn":"ADBE Vector Group","hd":false},{"ty":"mm","mm":5,"nm":"Merge Paths 1","mn":"ADBE Vector Filter - Merge","hd":false},{"ty":"fl","c":{"a":0,"k":[0.964705882353,0.972549019608,0.996078431373,1],"ix":4},"o":{"a":0,"k":100,"ix":5},"r":1,"bm":0,"nm":"Fill 1","mn":"ADBE Vector Graphic - Fill","hd":false},{"ty":"tr","p":{"a":0,"k":[0,0],"ix":2},"a":{"a":0,"k":[0,0],"ix":1},"s":{"a":0,"k":[100,100],"ix":3},"r":{"a":0,"k":0,"ix":6},"o":{"a":0,"k":100,"ix":7},"sk":{"a":0,"k":0,"ix":4},"sa":{"a":0,"k":0,"ix":5},"nm":"Transform"}],"nm":"Group 1","np":4,"cix":2,"bm":0,"ix":1,"mn":"ADBE Vector Group","hd":false}],"ip":-30,"op":40,"st":-30,"bm":0},{"ddd":0,"ind":5,"ty":3,"nm":"Null 7","sr":1,"ks":{"o":{"a":0,"k":0,"ix":11},"r":{"a":0,"k":0,"ix":10},"p":{"s":true,"x":{"a":0,"k":500,"ix":3},"y":{"a":1,"k":[{"i":{"x":[0.04],"y":[1]},"o":{"x":[0.35],"y":[0]},"t":30,"s":[1510]},{"i":{"x":[0.833],"y":[1]},"o":{"x":[0.35],"y":[0]},"t":40,"s":[500]},{"i":{"x":[0.95],"y":[0.471]},"o":{"x":[0.85],"y":[0]},"t":70,"s":[500]},{"t":90,"s":[-626]}],"ix":4}},"a":{"a":0,"k":[0,0,0],"ix":1,"l":2},"s":{"a":0,"k":[100,100,100],"ix":6,"l":2}},"ao":0,"ip":30,"op":100,"st":30,"bm":0},{"ddd":0,"ind":6,"ty":4,"nm":"line","parent":5,"sr":1,"ks":{"o":{"a":0,"k":100,"ix":11},"r":{"a":0,"k":0,"ix":10},"p":{"a":0,"k":[0,0,0],"ix":2,"l":2},"a":{"a":0,"k":[0,0,0],"ix":1,"l":2},"s":{"a":0,"k":[100,100,100],"ix":6,"l":2}},"ao":0,"shapes":[{"ind":0,"ty":"sh","ix":1,"ks":{"a":0,"k":{"i":[[0,0],[0,0]],"o":[[0,0],[0,0]],"v":[[-499.875,-499.875],[579.25,579.5]],"c":false},"ix":2},"nm":"Path 1","mn":"ADBE Vector Shape - Group","hd":false},{"ty":"tm","s":{"a":0,"k":0,"ix":1},"e":{"a":1,"k":[{"i":{"x":[0.04],"y":[1]},"o":{"x":[0.35],"y":[0]},"t":40,"s":[0]},{"t":60,"s":[100]}],"ix":2},"o":{"a":0,"k":0,"ix":3},"m":1,"ix":2,"nm":"Trim Paths 1","mn":"ADBE Vector Filter - Trim","hd":false},{"ty":"st","c":{"a":0,"k":[0.964705884457,0.972549021244,0.996078431606,1],"ix":3},"o":{"a":0,"k":100,"ix":4},"w":{"a":0,"k":177,"ix":5},"lc":1,"lj":1,"ml":4,"bm":0,"nm":"Stroke 1","mn":"ADBE Vector Graphic - Stroke","hd":false}],"ip":30,"op":100,"st":30,"bm":0},{"ddd":0,"ind":7,"ty":4,"nm":"mask","parent":5,"td":1,"sr":1,"ks":{"o":{"a":0,"k":100,"ix":11},"r":{"a":0,"k":0,"ix":10},"p":{"a":0,"k":[0,0,0],"ix":2,"l":2},"a":{"a":0,"k":[0,0,0],"ix":1,"l":2},"s":{"a":0,"k":[100,100,100],"ix":6,"l":2}},"ao":0,"shapes":[{"ind":0,"ty":"sh","ix":1,"ks":{"a":0,"k":{"i":[[0,0],[0,0]],"o":[[0,0],[0,0]],"v":[[-499.875,-499.875],[500.25,500.5]],"c":false},"ix":2},"nm":"Path 1","mn":"ADBE Vector Shape - Group","hd":false},{"ty":"tm","s":{"a":0,"k":0,"ix":1},"e":{"a":1,"k":[{"i":{"x":[0.04],"y":[1]},"o":{"x":[0.35],"y":[0]},"t":40,"s":[0]},{"t":56,"s":[100]}],"ix":2},"o":{"a":0,"k":0,"ix":3},"m":1,"ix":2,"nm":"Trim Paths 1","mn":"ADBE Vector Filter - Trim","hd":false},{"ty":"st","c":{"a":0,"k":[1,0,0,1],"ix":3},"o":{"a":0,"k":100,"ix":4},"w":{"a":0,"k":362,"ix":5},"lc":1,"lj":1,"ml":4,"bm":0,"nm":"Stroke 1","mn":"ADBE Vector Graphic - Stroke","hd":false}],"ip":30,"op":100,"st":30,"bm":0},{"ddd":0,"ind":8,"ty":4,"nm":"chain","parent":5,"tt":2,"sr":1,"ks":{"o":{"a":0,"k":100,"ix":11},"r":{"a":0,"k":0,"ix":10},"p":{"a":0,"k":[-0.001,0,0],"ix":2,"l":2},"a":{"a":0,"k":[0,0,0],"ix":1,"l":2},"s":{"a":0,"k":[100,100,100],"ix":6,"l":2}},"ao":0,"shapes":[{"ty":"gr","it":[{"ty":"gr","it":[{"ind":0,"ty":"sh","ix":1,"ks":{"a":0,"k":{"i":[[113.903,113.903],[74.644,0],[56.953,-56.952],[0,0],[0,0],[-113.903,-113.903],[-74.644,0],[-56.953,56.951],[0,0],[0,0],[0,0],[0,0],[0,0],[0,0]],"o":[[-56.952,-56.951],[-74.644,0],[0,0],[0,0],[-113.903,113.903],[56.952,56.951],[74.644,0],[0,0],[0,0],[0,0],[0,0],[0,0],[0,0],[113.903,-113.904]],"v":[[414.572,-414.573],[208.334,-500],[2.095,-414.573],[-78.712,-333.767],[-414.572,2.094],[-414.572,414.573],[-208.332,500],[-2.093,414.573],[78.714,333.767],[78.714,333.767],[88.06,324.42],[90.466,322.014],[90.466,322.014],[414.572,-2.094]],"c":true},"ix":2},"nm":"Path 1","mn":"ADBE Vector Shape - Group","hd":false},{"ty":"tr","p":{"a":0,"k":[0,0],"ix":2},"a":{"a":0,"k":[0,0],"ix":1},"s":{"a":0,"k":[100,100],"ix":3},"r":{"a":0,"k":0,"ix":6},"o":{"a":0,"k":100,"ix":7},"sk":{"a":0,"k":0,"ix":4},"sa":{"a":0,"k":0,"ix":5},"nm":"Transform"}],"nm":"Group 1","np":1,"cix":2,"bm":0,"ix":1,"mn":"ADBE Vector Group","hd":false},{"ty":"gr","it":[{"ind":0,"ty":"sh","ix":1,"ks":{"a":0,"k":{"i":[[19.674,-19.674],[0,0],[0,0],[0,0],[27.823,0],[19.674,19.675],[0,27.823],[-19.674,19.674],[0,0],[0,0],[-27.823,0],[-19.674,-19.675],[0,-27.824]],"o":[[0,0],[0,0],[0,0],[-19.675,19.676],[-27.823,0],[-19.674,-19.674],[0,-27.823],[0,0],[0,0],[19.675,-19.675],[27.823,0],[19.674,19.674],[0,27.824]],"v":[[281.989,-134.677],[-53.87,201.183],[-53.869,201.184],[-134.676,281.99],[-208.332,312.5],[-281.989,281.99],[-312.499,208.333],[-281.989,134.677],[53.871,-201.184],[134.676,-281.99],[208.332,-312.5],[281.989,-281.99],[312.499,-208.333]],"c":true},"ix":2},"nm":"Path 1","mn":"ADBE Vector Shape - Group","hd":false},{"ty":"tr","p":{"a":0,"k":[0.001,0],"ix":2},"a":{"a":0,"k":[0,0],"ix":1},"s":{"a":0,"k":[100,100],"ix":3},"r":{"a":0,"k":0,"ix":6},"o":{"a":0,"k":100,"ix":7},"sk":{"a":0,"k":0,"ix":4},"sa":{"a":0,"k":0,"ix":5},"nm":"Transform"}],"nm":"Group 2","np":1,"cix":2,"bm":0,"ix":2,"mn":"ADBE Vector Group","hd":false},{"ty":"mm","mm":5,"nm":"Merge Paths 1","mn":"ADBE Vector Filter - Merge","hd":false},{"ty":"fl","c":{"a":0,"k":[0.964705882353,0.972549019608,0.996078431373,1],"ix":4},"o":{"a":0,"k":100,"ix":5},"r":1,"bm":0,"nm":"Fill 1","mn":"ADBE Vector Graphic - Fill","hd":false},{"ty":"tr","p":{"a":0,"k":[0,0],"ix":2},"a":{"a":0,"k":[0,0],"ix":1},"s":{"a":0,"k":[100,100],"ix":3},"r":{"a":0,"k":0,"ix":6},"o":{"a":0,"k":100,"ix":7},"sk":{"a":0,"k":0,"ix":4},"sa":{"a":0,"k":0,"ix":5},"nm":"Transform"}],"nm":"Group 1","np":4,"cix":2,"bm":0,"ix":1,"mn":"ADBE Vector Group","hd":false}],"ip":30,"op":100,"st":30,"bm":0}],"markers":[]}