{"nm":"enable-biometrics-card","ddd":0,"h":408,"w":724,"meta":{"g":"@lottiefiles/toolkit-js 0.68.0"},"layers":[{"ty":4,"nm":"chip","sr":1,"st":0,"op":612,"ip":0,"ln":"7879","hasMask":false,"ao":0,"ks":{"a":{"a":0,"k":[0,0]},"s":{"a":1,"k":[{"s":[34.709,34.709,100],"i":{"x":[0.04,0.04,0.04],"y":[1,1,1]},"o":{"x":[0.35,0.35,0.35],"y":[0,0,0]},"t":49.836},{"s":[0,0,0],"i":{"x":[0.833,0.833,0.833],"y":[1,1,1]},"o":{"x":[0.167,0.167,0.167],"y":[0,0,0]},"t":67.8},{"s":[0,0,0],"i":{"x":[0.04,0.04,0.04],"y":[1,1,1]},"o":{"x":[0.35,0.35,0.35],"y":[0,0,0]},"t":488.996},{"s":[34.709,34.709,100],"i":{"x":[0.833,0.833,0.833],"y":[1,1,1]},"o":{"x":[0.167,0.167,0.167],"y":[0,0,0]},"t":519.996}]},"p":{"a":0,"k":[-238.728,320.926,0]},"r":{"a":0,"k":0},"sa":{"a":0,"k":0},"o":{"a":0,"k":100}},"shapes":[{"ty":"gr","nm":"Group 1","it":[{"ty":"rc","nm":"Rectangle Path 1","d":1,"p":{"a":0,"k":[0,0]},"r":{"a":0,"k":0},"s":{"a":0,"k":[76.197,126.995]}},{"ty":"fl","nm":"Fill 1","c":{"a":0,"k":[0.0353,0.0471,0.0667]},"r":1,"o":{"a":0,"k":100}},{"ty":"tr","a":{"a":0,"k":[0,0]},"s":{"a":0,"k":[100,100]},"p":{"a":0,"k":[127.018,0.02]},"r":{"a":0,"k":270},"sa":{"a":0,"k":0},"o":{"a":0,"k":100}}]},{"ty":"gr","nm":"Group 2","it":[{"ty":"rc","nm":"Rectangle Path 1","d":1,"p":{"a":0,"k":[0,0]},"r":{"a":0,"k":0},"s":{"a":0,"k":[126.995,76.197]}},{"ty":"fl","nm":"Fill 1","c":{"a":0,"k":[0.0353,0.0471,0.0667]},"r":1,"o":{"a":0,"k":100}},{"ty":"tr","a":{"a":0,"k":[0,0]},"s":{"a":0,"k":[100,100]},"p":{"a":0,"k":[-127.018,-0.006]},"r":{"a":0,"k":0},"sa":{"a":0,"k":0},"o":{"a":0,"k":100}}]},{"ty":"gr","nm":"Group 3","it":[{"ty":"sh","nm":"Path 1","d":1,"ks":{"a":0,"k":{"c":true,"i":[[0,0],[0,0],[0,0],[0,0],[0,0],[0,0]],"o":[[0,0],[0,0],[0,0],[0,0],[0,0],[0,0]],"v":[[-190.493,23.283],[-142.869,69.847],[142.87,69.847],[190.493,23.283],[190.493,-69.847],[-190.493,-69.847]]}}},{"ty":"fl","nm":"Fill 1","c":{"a":0,"k":[0.0353,0.0471,0.0667]},"r":1,"o":{"a":0,"k":100}},{"ty":"tr","a":{"a":0,"k":[0,0]},"s":{"a":0,"k":[100,100]},"p":{"a":0,"k":[-0.009,130.653]},"r":{"a":0,"k":0},"sa":{"a":0,"k":0},"o":{"a":0,"k":100}}]},{"ty":"gr","nm":"Group 4","it":[{"ty":"sh","nm":"Path 1","d":1,"ks":{"a":0,"k":{"c":true,"i":[[0,0],[0,0],[0,0],[0,0],[0,0],[0,0]],"o":[[0,0],[0,0],[0,0],[0,0],[0,0],[0,0]],"v":[[190.493,-23.283],[142.869,-69.848],[-142.87,-69.848],[-190.493,-23.283],[-190.493,69.848],[190.493,69.848]]}}},{"ty":"fl","nm":"Fill 1","c":{"a":0,"k":[0.0353,0.0471,0.0667]},"r":1,"o":{"a":0,"k":100}},{"ty":"tr","a":{"a":0,"k":[0,0]},"s":{"a":0,"k":[100,100]},"p":{"a":0,"k":[-0.023,-130.652]},"r":{"a":0,"k":0},"sa":{"a":0,"k":0},"o":{"a":0,"k":100}}]}],"ind":1,"parent":4},{"ty":4,"nm":"head new","sr":1,"st":0,"op":1200,"ip":0,"ln":"7863","hasMask":true,"ao":0,"ks":{"a":{"a":0,"k":[0,-23,0]},"s":{"a":0,"k":[294.118,294.118,100]},"p":{"a":0,"k":[-1.452,-12.265,0]},"r":{"a":0,"k":0},"sa":{"a":0,"k":0},"o":{"a":0,"k":100}},"masksProperties":[{"nm":"Mask 1","inv":false,"mode":"s","x":{"a":0,"k":0},"o":{"a":0,"k":100},"pt":{"a":1,"k":[{"o":{"x":0.35,"y":0},"i":{"x":0.04,"y":1},"s":[{"c":true,"i":[[0,0],[0,0],[0,0],[0,0]],"o":[[0,0],[0,0],[0,0],[0,0]],"v":[[-79.333,-66.194],[-79.5,90],[79.5,90],[79.667,-66.194]]}],"t":49.836},{"o":{"x":0.167,"y":0},"i":{"x":0.833,"y":1},"s":[{"c":true,"i":[[0,0],[0,0],[0,0],[0,0]],"o":[[0,0],[0,0],[0,0],[0,0]],"v":[[-79.5,58.25],[-79.5,90],[79.5,90],[79.5,58.25]]}],"t":67.999},{"o":{"x":0.35,"y":0},"i":{"x":0.04,"y":1},"s":[{"c":true,"i":[[0,0],[0,0],[0,0],[0,0]],"o":[[0,0],[0,0],[0,0],[0,0]],"v":[[-79.5,58.25],[-79.5,90],[79.5,90],[79.5,58.25]]}],"t":158.999},{"o":{"x":0.35,"y":0},"i":{"x":0.833,"y":1},"s":[{"c":true,"i":[[0,0],[0,0],[0,0],[0,0]],"o":[[0,0],[0,0],[0,0],[0,0]],"v":[[-79.5,-66.037],[-79.5,90],[79.5,90],[79.5,-66.037]]}],"t":183.999},{"o":{"x":0.32,"y":0},"i":{"x":0.04,"y":1},"s":[{"c":true,"i":[[0,0],[0,0],[0,0],[0,0]],"o":[[0,0],[0,0],[0,0],[0,0]],"v":[[-79.5,-66.037],[-79.5,90],[79.5,90],[79.5,-66.037]]}],"t":328.997},{"o":{"x":0.167,"y":0},"i":{"x":0.833,"y":1},"s":[{"c":true,"i":[[0,0],[0,0],[0,0],[0,0]],"o":[[0,0],[0,0],[0,0],[0,0]],"v":[[-79.5,58.25],[-79.5,90],[79.5,90],[79.5,58.25]]}],"t":352.997},{"o":{"x":0.35,"y":0},"i":{"x":0.04,"y":1},"s":[{"c":true,"i":[[0,0],[0,0],[0,0],[0,0]],"o":[[0,0],[0,0],[0,0],[0,0]],"v":[[-79.5,58.25],[-79.5,90],[79.5,90],[79.5,58.25]]}],"t":488.996},{"s":[{"c":true,"i":[[0,0],[0,0],[0,0],[0,0]],"o":[[0,0],[0,0],[0,0],[0,0]],"v":[[-79.333,-66.194],[-79.5,90],[79.5,90],[79.667,-66.194]]}],"t":519.996}]}}],"shapes":[{"ty":"el","nm":"Ellipse Path 1","d":1,"p":{"a":0,"k":[0,1]},"s":{"a":0,"k":[132,132]}},{"ty":"fl","nm":"Fill 1","c":{"a":0,"k":[0.9608,0.9725,1]},"r":1,"o":{"a":0,"k":100}}],"ind":2,"parent":6},{"ty":3,"nm":"Null 1","sr":1,"st":-39,"op":1161,"ip":-39,"ln":"7862","hasMask":false,"ao":0,"ks":{"a":{"a":0,"k":[0,0]},"s":{"a":0,"k":[34,34,103.03]},"p":{"a":0,"k":[362.5,284.5,0]},"r":{"a":0,"k":0},"sa":{"a":0,"k":0},"o":{"a":0,"k":100}},"ind":3},{"ty":3,"nm":"Null 2","sr":1,"st":0,"op":1200,"ip":0,"ln":"7861","hasMask":false,"ao":0,"ks":{"a":{"a":0,"k":[0,0]},"s":{"a":0,"k":[100,100]},"p":{"s":true,"x":{"a":0,"k":0},"y":{"a":1,"k":[{"o":{"x":0.194,"y":0.565},"i":{"x":0.04,"y":0.633},"s":[-184],"t":39.857},{"o":{"x":0.35,"y":-0.026},"i":{"x":0.029,"y":0.916},"s":[-200.444],"t":49.836},{"o":{"x":0.429,"y":-0.076},"i":{"x":0.04,"y":1},"s":[38],"t":69.999},{"o":{"x":0.167,"y":0},"i":{"x":0.833,"y":1},"s":[0],"t":78.999},{"o":{"x":0.35,"y":0},"i":{"x":0.04,"y":1},"s":[0],"t":202.998},{"o":{"x":0.35,"y":0},"i":{"x":0.04,"y":1},"s":[17],"t":204.998},{"o":{"x":0.167,"y":0},"i":{"x":0.833,"y":1},"s":[0],"t":212.998},{"o":{"x":0.35,"y":0},"i":{"x":0,"y":0.891},"s":[0],"t":483.996},{"o":{"x":0.387,"y":-0.038},"i":{"x":0,"y":1},"s":[47.741],"t":488.996},{"s":[-184],"t":519.996}]},"z":{"a":0,"k":0}},"r":{"a":0,"k":0},"sa":{"a":0,"k":0},"o":{"a":0,"k":100}},"ind":4,"parent":3},{"ty":4,"nm":"lock 2","sr":1,"st":0,"op":415,"ip":160,"ln":"7860","hasMask":false,"ao":0,"ks":{"a":{"a":0,"k":[0,0]},"s":{"a":0,"k":[100,100]},"p":{"s":true,"x":{"a":0,"k":-1.471},"y":{"a":1,"k":[{"o":{"x":0.35,"y":0},"i":{"x":0.074,"y":1.063},"s":[-224.5],"t":162.999},{"o":{"x":1,"y":0.054},"i":{"x":0.956,"y":0.538},"s":[-320.5],"t":184.999},{"o":{"x":0.167,"y":0},"i":{"x":0.833,"y":1},"s":[-224.5],"t":202.998},{"o":{"x":0.047,"y":0.153},"i":{"x":0,"y":1.044},"s":[-224.5],"t":328.997},{"o":{"x":0.553,"y":0.11},"i":{"x":0.04,"y":1},"s":[-314.147],"t":345.997},{"o":{"x":0.167,"y":0},"i":{"x":0.833,"y":1},"s":[-224.5],"t":408.997},{"s":[-224.5],"t":414.997}]},"z":{"a":0,"k":0}},"r":{"a":0,"k":0},"sa":{"a":0,"k":0},"o":{"a":0,"k":100}},"shapes":[{"ty":"gr","nm":"Group 1","it":[{"ty":"sh","nm":"Path 1","d":1,"ks":{"a":1,"k":[{"o":{"x":0.67,"y":0},"i":{"x":0.04,"y":1},"s":[{"c":true,"i":[[0,0],[0,0],[32.022,0],[0,-0.341],[0,0],[0,0],[0,0],[-107.133,0],[0,-107.133],[0,0]],"o":[[0,0],[0.842,0],[-31.928,0],[0,0],[0,0],[0,0],[0,-107.133],[107.133,0],[0,0],[0,0]],"v":[[57.981,58.438],[57.981,58.481],[-0.057,58.037],[-57.981,58.481],[-57.981,58.438],[-193.981,58.438],[-193.981,58.481],[0,-135.5],[193.981,58.481],[193.981,58.438]]}],"t":162.999},{"o":{"x":0.67,"y":0},"i":{"x":0.833,"y":1},"s":[{"c":true,"i":[[0,0],[0,0],[32.022,0],[0,-32.022],[0,0],[0,0],[0,0],[-107.133,0],[0,-107.133],[0,0]],"o":[[0,0],[0,-32.022],[-32.022,0],[0,0],[0,0],[0,0],[0,-107.133],[107.133,0],[0,0],[0,0]],"v":[[57.981,135.5],[57.981,58.481],[0,0.5],[-57.981,58.481],[-57.981,135.5],[-193.981,135.5],[-193.981,58.481],[0,-135.5],[193.981,58.481],[193.981,135.5]]}],"t":182.999},{"o":{"x":0.35,"y":0},"i":{"x":0.04,"y":1},"s":[{"c":true,"i":[[0,0],[0,0],[32.022,0],[0,-32.022],[0,0],[0,0],[0,0],[-107.133,0],[0,-107.133],[0,0]],"o":[[0,0],[0,-32.022],[-32.022,0],[0,0],[0,0],[0,0],[0,-107.133],[107.133,0],[0,0],[0,0]],"v":[[57.981,135.5],[57.981,58.481],[0,0.5],[-57.981,58.481],[-57.981,135.5],[-193.981,135.5],[-193.981,58.481],[0,-135.5],[193.981,58.481],[193.981,135.5]]}],"t":328.997},{"s":[{"c":true,"i":[[0,0],[0,0],[32.023,0],[0.628,0],[0,0],[0,0],[0,0],[-107.133,0],[0,-107.133],[0,0]],"o":[[0,0],[0,-0.407],[-32.022,0],[0,0],[0,0],[0,0],[0,-107.133],[107.133,0],[0,0],[0,0]],"v":[[57.981,58.438],[57.981,58.481],[-0.39,58.44],[-57.981,58.481],[-57.981,58.438],[-193.981,58.438],[-193.981,58.481],[0,-135.5],[193.981,58.481],[193.981,58.438]]}],"t":340.997}]}},{"ty":"fl","nm":"Fill 1","c":{"a":0,"k":[0.9608,0.9725,1]},"r":1,"o":{"a":0,"k":100}},{"ty":"tr","a":{"a":0,"k":[0,0]},"s":{"a":0,"k":[100,100]},"p":{"a":0,"k":[0,0]},"r":{"a":0,"k":0},"sa":{"a":0,"k":0},"o":{"a":0,"k":100}}]}],"ind":5,"parent":4},{"ty":4,"nm":"lock","sr":1,"st":0,"op":1200,"ip":0,"hd":true,"ln":"7859","hasMask":false,"ao":0,"ks":{"a":{"a":0,"k":[0,0]},"s":{"a":0,"k":[100,100]},"p":{"s":true,"x":{"a":0,"k":-0.019},"y":{"a":1,"k":[{"o":{"x":0.35,"y":0},"i":{"x":0.074,"y":1.063},"s":[-224.5],"t":162.999},{"o":{"x":1,"y":0.054},"i":{"x":0.956,"y":0.538},"s":[-320.5],"t":184.999},{"o":{"x":0.167,"y":0},"i":{"x":0.833,"y":1},"s":[-224.5],"t":202.998},{"o":{"x":0.047,"y":0.153},"i":{"x":0,"y":1.044},"s":[-224.5],"t":332.997},{"o":{"x":0.553,"y":0.103},"i":{"x":0.04,"y":1},"s":[-314.147],"t":349.997},{"s":[-224.5],"t":408.997}]},"z":{"a":0,"k":0}},"r":{"a":0,"k":0},"sa":{"a":0,"k":0},"o":{"a":0,"k":100}},"shapes":[{"ty":"gr","nm":"Group 1","it":[{"ty":"sh","nm":"Path 1","d":1,"ks":{"a":1,"k":[{"o":{"x":0.67,"y":0},"i":{"x":0.04,"y":1},"s":[{"c":true,"i":[[0,0],[0,0],[32.022,0],[0,-32.022],[0,0],[0,0],[0,0],[-107.133,0],[0,-107.133],[0,0]],"o":[[0,0],[0,-32.022],[-32.022,0],[0,0],[0,0],[0,0],[0,-107.133],[107.133,0],[0,0],[0,0]],"v":[[57.981,58.438],[57.981,58.481],[0,0.5],[-57.981,58.481],[-57.981,58.438],[-193.981,58.438],[-193.981,58.481],[0,-135.5],[193.981,58.481],[193.981,58.438]]}],"t":162.999},{"o":{"x":0.67,"y":0},"i":{"x":0.833,"y":1},"s":[{"c":true,"i":[[0,0],[0,0],[32.022,0],[0,-32.022],[0,0],[0,0],[0,0],[-107.133,0],[0,-107.133],[0,0]],"o":[[0,0],[0,-32.022],[-32.022,0],[0,0],[0,0],[0,0],[0,-107.133],[107.133,0],[0,0],[0,0]],"v":[[57.981,135.5],[57.981,58.481],[0,0.5],[-57.981,58.481],[-57.981,135.5],[-193.981,135.5],[-193.981,58.481],[0,-135.5],[193.981,58.481],[193.981,135.5]]}],"t":182.999},{"o":{"x":0.35,"y":0},"i":{"x":0.04,"y":1},"s":[{"c":true,"i":[[0,0],[0,0],[32.022,0],[0,-32.022],[0,0],[0,0],[0,0],[-107.133,0],[0,-107.133],[0,0]],"o":[[0,0],[0,-32.022],[-32.022,0],[0,0],[0,0],[0,0],[0,-107.133],[107.133,0],[0,0],[0,0]],"v":[[57.981,135.5],[57.981,58.481],[0,0.5],[-57.981,58.481],[-57.981,135.5],[-193.981,135.5],[-193.981,58.481],[0,-135.5],[193.981,58.481],[193.981,135.5]]}],"t":333.997},{"s":[{"c":true,"i":[[0,0],[0,0],[32.022,0],[0,-32.022],[0,0],[0,0],[0,0],[-107.133,0],[0,-107.133],[0,0]],"o":[[0,0],[0,-32.022],[-32.022,0],[0,0],[0,0],[0,0],[0,-107.133],[107.133,0],[0,0],[0,0]],"v":[[57.981,58.438],[57.981,58.481],[0,0.5],[-57.981,58.481],[-57.981,58.438],[-193.981,58.438],[-193.981,58.481],[0,-135.5],[193.981,58.481],[193.981,58.438]]}],"t":345.997}]}},{"ty":"fl","nm":"Fill 1","c":{"a":0,"k":[0.9608,0.9725,1]},"r":1,"o":{"a":0,"k":100}},{"ty":"tr","a":{"a":0,"k":[0,0]},"s":{"a":0,"k":[100,100]},"p":{"a":0,"k":[0,0]},"r":{"a":0,"k":0},"sa":{"a":0,"k":0},"o":{"a":0,"k":100}}]}],"ind":6,"parent":4},{"ty":4,"nm":"body","sr":1,"st":0,"op":1200,"ip":0,"ln":"7857","hasMask":false,"ao":0,"ks":{"a":{"a":0,"k":[0,0]},"s":{"a":0,"k":[100,100]},"p":{"a":0,"k":[0,225.375,0]},"r":{"a":0,"k":0},"sa":{"a":0,"k":0},"o":{"a":0,"k":100}},"shapes":[{"ty":"gr","nm":"Group 1","it":[{"ty":"sh","nm":"Path 1","d":1,"ks":{"a":1,"k":[{"o":{"x":0.35,"y":0},"i":{"x":0.04,"y":1},"s":[{"c":true,"i":[[0,0],[0,0],[0,0],[0,0],[0,0],[0,0],[0,0],[0,0]],"o":[[0,0],[0,0],[0,0],[0,0],[0,0],[0,0],[0,0],[0,0]],"v":[[-325.226,-134.722],[323.58,-134.722],[358.966,-97.559],[358.92,290.13],[326.106,322.007],[-326.955,322.007],[-359.08,290.13],[-359.215,-100.852]]}],"t":49.836},{"o":{"x":0.167,"y":0},"i":{"x":0.833,"y":1},"s":[{"c":true,"i":[[0,0],[0,0],[0,0],[0,0],[0,0],[0,0],[0,0],[0,0]],"o":[[0,0],[0,0],[0,0],[0,0],[0,0],[0,0],[0,0],[0,0]],"v":[[-269.25,-134.625],[269.25,-134.625],[359,-44.875],[359,134.625],[320.952,134.625],[-326.009,134.625],[-359,134.625],[-359,-44.875]]}],"t":67.8},{"o":{"x":0.35,"y":0},"i":{"x":0.04,"y":1},"s":[{"c":true,"i":[[0,0],[0,0],[0,0],[0,0],[0,0],[0,0],[0,0],[0,0]],"o":[[0,0],[0,0],[0,0],[0,0],[0,0],[0,0],[0,0],[0,0]],"v":[[-269.25,-134.625],[269.25,-134.625],[359,-44.875],[359,134.625],[320.952,134.625],[-326.009,134.625],[-359,134.625],[-359,-44.875]]}],"t":162.999},{"o":{"x":0.167,"y":0},"i":{"x":0.833,"y":1},"s":[{"c":true,"i":[[0,0],[0,0],[0,0],[0,0],[0,0],[0,0],[0,0],[0,0]],"o":[[0,0],[0,0],[0,0],[0,0],[0,0],[0,0],[0,0],[0,0]],"v":[[-269.5,-286.125],[269,-286.125],[358.75,-196.375],[359,134.625],[320.952,134.625],[-326.009,134.625],[-359,134.625],[-359.25,-196.375]]}],"t":199.998},{"o":{"x":0.14,"y":0.007},"i":{"x":0.04,"y":1},"s":[{"c":true,"i":[[0,0],[0,0],[0,0],[0,0],[0,0],[0,0],[0,0],[0,0]],"o":[[0,0],[0,0],[0,0],[0,0],[0,0],[0,0],[0,0],[0,0]],"v":[[-269.5,-286.125],[269,-286.125],[358.75,-196.375],[359,134.625],[320.952,134.625],[-326.009,134.625],[-359,134.625],[-359.25,-196.375]]}],"t":334.997},{"o":{"x":0.167,"y":0},"i":{"x":0.833,"y":1},"s":[{"c":true,"i":[[0,0],[0,0],[0,0],[0,0],[0,0],[0,0],[0,0],[0,0]],"o":[[0,0],[0,0],[0,0],[0,0],[0,0],[0,0],[0,0],[0,0]],"v":[[-269.25,-134.625],[269.25,-134.625],[359,-44.875],[359,134.625],[320.952,134.625],[-326.009,134.625],[-359,134.625],[-359,-44.875]]}],"t":401.997},{"o":{"x":0.35,"y":0},"i":{"x":0.04,"y":1},"s":[{"c":true,"i":[[0,0],[0,0],[0,0],[0,0],[0,0],[0,0],[0,0],[0,0]],"o":[[0,0],[0,0],[0,0],[0,0],[0,0],[0,0],[0,0],[0,0]],"v":[[-269.25,-134.625],[269.25,-134.625],[359,-44.875],[359,134.625],[320.952,134.625],[-326.009,134.625],[-359,134.625],[-359,-44.875]]}],"t":488.996},{"s":[{"c":true,"i":[[0,0],[0,0],[0,0],[0,0],[0,0],[0,0],[0,0],[0,0]],"o":[[0,0],[0,0],[0,0],[0,0],[0,0],[0,0],[0,0],[0,0]],"v":[[-325.226,-134.722],[323.58,-134.722],[358.966,-97.559],[358.92,290.13],[326.106,322.007],[-326.955,322.007],[-359.08,290.13],[-359.215,-100.852]]}],"t":519.996}]}},{"ty":"fl","nm":"Fill 1","c":{"a":0,"k":[0.9608,0.9725,1]},"r":1,"o":{"a":0,"k":100}},{"ty":"tr","a":{"a":0,"k":[0,0]},"s":{"a":0,"k":[100,100]},"p":{"a":0,"k":[0,0]},"r":{"a":0,"k":0},"sa":{"a":0,"k":0},"o":{"a":0,"k":100}}]}],"ind":7,"parent":4}],"v":"5.7.0","fr":60,"op":601,"ip":0,"assets":[]}